django_singleton_admin/__init__.py
django_singleton_admin/admin.py
django_singleton_admin/apps.py
django_singleton_admin/templates/django_singleton_admin/change_form.html
django_singleton_admin_2-1.0.4.dist-info/LICENSE
django_singleton_admin_2-1.0.4.dist-info/METADATA
django_singleton_admin_2-1.0.4.dist-info/WHEEL
django_singleton_admin_2-1.0.4.dist-info/top_level.txt
django_singleton_admin_2-1.0.4.dist-info/RECORD
